yamlgenerator_hook_validate/__init__.py
yamlgenerator_hook_validate-1.0.0.dist-info/METADATA
yamlgenerator_hook_validate-1.0.0.dist-info/WHEEL
yamlgenerator_hook_validate-1.0.0.dist-info/RECORD
