Metadata-Version: 2.1
Name: yamlgenerator-hook-validate
Version: 1.0.0
Summary: 
License: MIT
Author: kaixinol
Author-email: keiplyer@gmail.com
Requires-Python: >=3.11,<4.0
Classifier: License :: OSI Approved :: MIT License
Classifier: Programming Language :: Python :: 3
Classifier: Programming Language :: Python :: 3.11
Classifier: Programming Language :: Python :: 3.12
Classifier: Programming Language :: Python :: 3.13
Requires-Dist: gameyamlspiderandgenerator (>=2.0.0b2,<3.0)
Requires-Dist: jsonschema (>=4.17.3)
Requires-Dist: loguru (>=0.7.0,<1.0)
